matematika.py
matematika-0.0.1.dist-info/WHEEL
matematika-0.0.1.dist-info/METADATA
matematika-0.0.1.dist-info/RECORD
